aws_region_proximity/__init__.py
aws_region_proximity/__version__.py
aws_region_proximity/aws-regions.json
aws_region_proximity/aws_objects.py
aws_region_proximity/command_line.py
aws_region_proximity-0.1.3.dist-info/LICENSE
aws_region_proximity-0.1.3.dist-info/METADATA
aws_region_proximity-0.1.3.dist-info/WHEEL
aws_region_proximity-0.1.3.dist-info/entry_points.txt
aws_region_proximity-0.1.3.dist-info/top_level.txt
aws_region_proximity-0.1.3.dist-info/zip-safe
aws_region_proximity-0.1.3.dist-info/RECORD
