Metadata-Version: 2.1
Name: aws-region-proximity
Version: 0.1.3
Summary: Generates a list of AWS regions closest to each other
Home-page: https://github.com/phistrom/aws-region-proximity
Author: Phillip Stromberg
Author-email: phillip@strombergs.com
License: MIT
Platform: UNKNOWN
License-File: LICENSE
Requires-Dist: haversine
